liveConsole/__init__.py
liveconsole-1.7.10.dist-info/licenses/LICENSE
pysole/__init__.py
pysole/__main__.py
pysole/commandHistory.py
pysole/helpTab.py
pysole/liveConsole.py
pysole/mainConsole.py
pysole/pysole.py
pysole/settings.json
pysole/styledTextbox.py
pysole/suggestionManager.py
pysole/themes.json
pysole/utils.py
liveconsole-1.7.10.dist-info/METADATA
liveconsole-1.7.10.dist-info/WHEEL
liveconsole-1.7.10.dist-info/entry_points.txt
liveconsole-1.7.10.dist-info/top_level.txt
liveconsole-1.7.10.dist-info/RECORD
