Metadata-Version: 2.4
Name: liveConsole
Version: 1.7.10
Summary: An IDLE-like debugger to allow for real-time command injection for debugging and testing python code
Author-email: Tzur Soffer <tzur.soffer@gmail.com>
License: MIT
Project-URL: Homepage, https://github.com/TzurSoffer/Pysole
Project-URL: Repository, https://github.com/TzurSoffer/Pysole
Requires-Python: >=3.7
License-File: LICENSE
Requires-Dist: customtkinter
Requires-Dist: pygments
Dynamic: license-file
